pybeatsaber/__init__.py
pybeatsaber/datatype.py
pybeatsaber/utils.py
pybeatsaber-0.0.2.dist-info/METADATA
pybeatsaber-0.0.2.dist-info/WHEEL
pybeatsaber-0.0.2.dist-info/top_level.txt
pybeatsaber-0.0.2.dist-info/RECORD
