Metadata-Version: 2.1
Name: pybeatsaber
Version: 0.0.2
Summary: BeatSaber beatmap IO library written in pure python
Home-page: https://github.com/Kitsunetic/pybeatsaber.git
Author: Kitsunetic
Author-email: jh.shim.gg@gmail.com
Classifier: Programming Language :: Python :: 3
Classifier: License :: OSI Approved :: MIT License
Classifier: Operating System :: OS Independent
Requires-Python: >=3
